textractmanifest/__init__.py
textractmanifest/manifest.py
amazon_textract_idp_cdk_manifest-0.0.1.dist-info/LICENSE
amazon_textract_idp_cdk_manifest-0.0.1.dist-info/METADATA
amazon_textract_idp_cdk_manifest-0.0.1.dist-info/WHEEL
amazon_textract_idp_cdk_manifest-0.0.1.dist-info/top_level.txt
amazon_textract_idp_cdk_manifest-0.0.1.dist-info/RECORD
