Metadata-Version: 2.1
Name: amazon-textract-idp-cdk-manifest
Version: 0.0.1
Summary: Amazon Textract IDP CDK Manifest
Home-page: https://github.com/aws-samples/amazon-textract-textractor/tree/master/idp_cdk_manifest
Author: Amazon Rekognition Textract Demoes
Author-email: rekognition-textract-demos@amazon.com
License: Apache License Version 2.0
Keywords: textract manifest
Platform: UNKNOWN
Classifier: Development Status :: 4 - Beta
Classifier: Topic :: Utilities
Classifier: License :: OSI Approved :: Apache Software License
Classifier: Programming Language :: Python :: 3.7
Classifier: Programming Language :: Python :: 3.8
Classifier: Programming Language :: Python :: 3.9
Requires-Python: >=3.7
Requires-Dist: marshmallow
Provides-Extra: testing
Requires-Dist: pytest ; extra == 'testing'
